ozon_api/__init__.py
ozon_api/base.py
ozon_api/exceptions.py
ozon_api/methods/__init__.py
ozon_api/methods/category.py
ozon_api/methods/product_archive.py
ozon_api/methods/product_barcode_add.py
ozon_api/methods/product_barcode_generate.py
ozon_api/methods/product_import.py
ozon_api/methods/product_info_attributes.py
ozon_api/methods/product_info_list.py
ozon_api/methods/product_list.py
ozon_api/methods/product_pictures.py
ozon_api/methods/product_pictures_info.py
ozon_api/methods/product_rating.py
ozon_api/methods/product_related_sku.py
ozon_api/methods/product_subscription.py
ozon_api/methods/product_update_offer_id.py
ozon_api/methods/products_delete_without_sku.py
ozon_api/methods/upload_digital_codes_info.py
ozon_api/models/__init__.py
ozon_api/models/category_attribute.py
ozon_api/models/category_tree.py
ozon_api/models/import_by_sku.py
ozon_api/models/product_archive.py
ozon_api/models/product_attributes_update.py
ozon_api/models/product_barcode_add.py
ozon_api/models/product_barcode_generate.py
ozon_api/models/product_import.py
ozon_api/models/product_import_info.py
ozon_api/models/product_info_attributes.py
ozon_api/models/product_info_list.py
ozon_api/models/product_list.py
ozon_api/models/product_pictures_info.py
ozon_api/models/product_rating.py
ozon_api/models/product_related_sku.py
ozon_api/models/product_subscription.py
ozon_api/models/product_update_offer_id.py
ozon_api/models/products_delete.py
ozon_api/models/products_delete_without_sku.py
ozon_api/models/upload_digital_codes.py
ozon_api/models/upload_digital_codes_info.py
ozon_api-1.5.0.dist-info/METADATA
ozon_api-1.5.0.dist-info/WHEEL
ozon_api-1.5.0.dist-info/licenses/LICENSE
ozon_api-1.5.0.dist-info/licenses/NOTICE
ozon_api-1.5.0.dist-info/RECORD
