Metadata-Version: 2.4
Name: ozon-api
Version: 1.5.0
Summary: Library for interacting with the Ozon API
Project-URL: Repository, https://github.com/mephistofox/python-ozon-api
Project-URL: Documentation, https://github.com/mephistofox/python-ozon-api/blob/main/README.md
Author-email: FxCode <dev@fxcode.ru>
License-Expression: MIT
License-File: LICENSE
License-File: NOTICE
Classifier: Topic :: Software Development :: Build Tools
Classifier: Topic :: Software Development :: Libraries :: Python Modules
Requires-Python: ~=3.10
Requires-Dist: aiohttp<4,>=3.10.5
Requires-Dist: build>=1.2.2.post1
Requires-Dist: loguru<0.8,>=0.7.2
Requires-Dist: pydantic<3,>=2.9.2
Requires-Dist: python-semantic-release>=10.2.0
Requires-Dist: tenacity>=9.1.2
